easymp3/__init__.py
easymp3/easymp3.py
easymp3/exception.py
easymp3/tag.py
easymp3/util.py
easymp3-1.3.2.dist-info/LICENSE
easymp3-1.3.2.dist-info/METADATA
easymp3-1.3.2.dist-info/WHEEL
easymp3-1.3.2.dist-info/top_level.txt
easymp3-1.3.2.dist-info/RECORD
