Metadata-Version: 2.1
Name: easymp3
Version: 1.3.2
Summary: Easily tag and manipulate MP3 files in a programmatic way.
Author: Chase Minert
Author-email: cminert58@gmail.com
License-File: LICENSE
Requires-Dist: mutagen ==1.47.0
